perfwatch/__init__.py
perfwatch/__main__.py
perfwatch/src/__init__.py
perfwatch/src/cache/__init__.py
perfwatch/src/cache/profiler.py
perfwatch/src/cpu/__init__.py
perfwatch/src/cpu/profiler.py
perfwatch/src/gpu/__init__.py
perfwatch/src/gpu/profiler.py
perfwatch/src/io/__init__.py
perfwatch/src/io/profiler.py
perfwatch/src/network/__init__.py
perfwatch/src/network/profiler.py
perfwatch/src/system/__init__.py
perfwatch/src/system/parser.py
perfwatch/src/system/profiler.py
perfwatch/src/thread/__init__.py
perfwatch/src/thread/profiler.py
perfwatch/src/watcher.py
perfwatch/utils/__init__.py
perfwatch/utils/logger.py
perfwatch-1.6.5.dist-info/METADATA
perfwatch-1.6.5.dist-info/WHEEL
perfwatch-1.6.5.dist-info/RECORD
