Metadata-Version: 2.1
Name: perfwatch
Version: 1.6.5
Summary: Python code performace metrics calculation tool
License: MIT
Author: Khushiyant
Author-email: khushiyant2002@gmail.com
Requires-Python: >=3.10,<4.0
Classifier: License :: OSI Approved :: MIT License
Classifier: Programming Language :: Python :: 3
Classifier: Programming Language :: Python :: 3.10
Classifier: Programming Language :: Python :: 3.11
Classifier: Programming Language :: Python :: 3.12
Requires-Dist: cachetools (>=5.4.0,<6.0.0)
Requires-Dist: line-profiler (>=4.1.3,<5.0.0)
Requires-Dist: memory-profiler (>=0.61.0,<0.62.0)
Requires-Dist: nvidia-ml-py3 (>=7.352.0,<8.0.0)
Requires-Dist: psutil (>=5.9.8,<6.0.0)
Requires-Dist: python-dotenv (>=1.0.1,<2.0.0)
Requires-Dist: scapy (>=2.5.0,<3.0.0)
Requires-Dist: sentry-sdk (>=2.13.0,<3.0.0)
Requires-Dist: tabulate (>=0.9.0,<0.10.0)
